indodax/Price.py
indodax/__init__.py
indodax-1.3.2.dist-info/LICENSE
indodax-1.3.2.dist-info/METADATA
indodax-1.3.2.dist-info/WHEEL
indodax-1.3.2.dist-info/top_level.txt
indodax-1.3.2.dist-info/RECORD
