Metadata-Version: 2.1
Name: indodax
Version: 1.3.2
Summary: paket ini untuk jual beli di indodax
Home-page: https://github.com/Mame29/Indodax
Author: Mame29
Author-email: evanr0240@gmail.com
Classifier: Programming Language :: Python :: 3
Classifier: License :: OSI Approved :: MIT License
Classifier: Operating System :: OS Independent
Requires-Python: >=3.6
License-File: LICENSE
Requires-Dist: requests
